cms_shiny/__init__.py
cms_shiny/admin.py
cms_shiny/cms_app.py
cms_shiny/cms_plugins.py
cms_shiny/cms_toolbar.py
cms_shiny/menu.py
cms_shiny/models.py
cms_shiny/tests.py
cms_shiny/urls.py
cms_shiny/views.py
cms_shiny/static/cms_shiny/app.css
cms_shiny/static/cms_shiny/app.js
cms_shiny/static/cms_shiny/jquery.matchHeight-min.js
cms_shiny/templates/cms_shiny/_shiny_app_info.html
cms_shiny/templates/cms_shiny/_shiny_list_item.html
cms_shiny/templates/cms_shiny/plugin.html
cms_shiny/templates/cms_shiny/shiny_detail.html
cms_shiny/templates/cms_shiny/shiny_list.html
djangocms_shiny_app-0.1.3.dist-info/DESCRIPTION.rst
djangocms_shiny_app-0.1.3.dist-info/METADATA
djangocms_shiny_app-0.1.3.dist-info/RECORD
djangocms_shiny_app-0.1.3.dist-info/WHEEL
djangocms_shiny_app-0.1.3.dist-info/metadata.json
djangocms_shiny_app-0.1.3.dist-info/top_level.txt
