Metadata-Version: 2.0
Name: djangocms-shiny-app
Version: 0.1.3
Summary: A Django app for adding R Shiny apps to a Django site with django CMS-specific features
Home-page: https://github.com/mfcovington/djangocms-shiny-app
Author: Michael F. Covington
Author-email: mfcovington@gmail.com
License: BSD License
Keywords: bioinformatics visualization cran r rstudio shiny shinyapp
Platform: UNKNOWN
Classifier: Development Status :: 3 - Alpha
Classifier: Environment :: Web Environment
Classifier: Framework :: Django
Classifier: Framework :: Django :: 1.7
Classifier: Framework :: Django :: 1.8
Classifier: Intended Audience :: Developers
Classifier: Intended Audience :: Science/Research
Classifier: License :: OSI Approved :: BSD License
Classifier: Operating System :: OS Independent
Classifier: Programming Language :: Python
Classifier: Programming Language :: Python :: 3
Classifier: Programming Language :: Python :: 3.2
Classifier: Programming Language :: Python :: 3.3
Classifier: Programming Language :: Python :: 3.4
Classifier: Programming Language :: Python :: 3 :: Only
Classifier: Topic :: Internet :: WWW/HTTP
Classifier: Topic :: Internet :: WWW/HTTP :: Dynamic Content
Classifier: Topic :: Scientific/Engineering :: Bio-Informatics
Classifier: Topic :: Scientific/Engineering :: Visualization
Requires-Dist: Django (>=1.7)
Requires-Dist: django-cms (>=3.0.7,<3.2)
Requires-Dist: django-filer (>=0.9.10)
